sum_4914/__init__.py
sum_4914-0.0.1.dist-info/METADATA
sum_4914-0.0.1.dist-info/WHEEL
sum_4914-0.0.1.dist-info/top_level.txt
sum_4914-0.0.1.dist-info/RECORD
